ace_hunter/__init__.py
ace_hunter/cli.py
ace_hunter/config.py
ace_hunter/query_hunter.py
ace_hunter/splunk.py
ace_hunter/util.py
ace_hunter/etc/defaults.ini
ace_hunter/hunt_type/__init__.py
ace_hunter/hunt_type/splunk.py
ace_hunter-1.0.2.dist-info/LICENSE
ace_hunter-1.0.2.dist-info/METADATA
ace_hunter-1.0.2.dist-info/WHEEL
ace_hunter-1.0.2.dist-info/entry_points.txt
ace_hunter-1.0.2.dist-info/top_level.txt
ace_hunter-1.0.2.dist-info/RECORD
