Metadata-Version: 2.1
Name: ace-hunter
Version: 1.0.2
Summary: Python library and command line tool hunting in ACE ecosystems.
Home-page: https://github.com/ace-ecosystem/ace-hunter
Author: Sean McFeely
Author-email: mcfeelynaes@gmail.com
License: UNKNOWN
Project-URL: Bug Tracker, https://github.com/ace-ecosystem/ace-hunter/issues
Keywords: ACE,hunting
Platform: UNKNOWN
Classifier: Development Status :: 3 - Alpha
Classifier: Intended Audience :: Developers
Classifier: Intended Audience :: Information Technology
Classifier: Programming Language :: Python :: 3
Classifier: License :: OSI Approved :: Apache Software License
Classifier: Operating System :: OS Independent
Requires-Python: >=3.7
License-File: LICENSE
Requires-Dist: ace-api (>=1.0.7)
Requires-Dist: coloredlogs
Requires-Dist: requests
Requires-Dist: croniter
